LICENSE.txt
README.md
requirements.txt
setup.cfg
setup.py
dist/realityengines-0.6.0b1.tar.gz
realityengines/api_key.py
realityengines/batch_prediction.py
realityengines/bucket_verification.py
realityengines/bucket_verification_instructions.py
realityengines/bucket_verification_result.py
realityengines/client.py
realityengines/dataset.py
realityengines/dataset_upload.py
realityengines/dataset_version.py
realityengines/deployment.py
realityengines/deployment_auth_token.py
realityengines/model.py
realityengines/model_metrics.py
realityengines/model_version.py
realityengines/project.py
realityengines/project_dataset.py
realityengines/project_validation.py
realityengines/refresh_pipeline_run.py
realityengines/refresh_policy.py
realityengines/schema.py
realityengines/streaming_auth_token.py
realityengines/training_config_options.py
realityengines/use_case.py
realityengines/use_case_requirements.py
realityengines.egg-info/PKG-INFO
realityengines.egg-info/SOURCES.txt
realityengines.egg-info/dependency_links.txt
realityengines.egg-info/requires.txt
realityengines.egg-info/top_level.txt
realityengines.egg-info/zip-safe