Metadata-Version: 1.1
Name: realityengines
Version: 0.9.1
Summary: Abacus.AI Python Client Library
Home-page: https://abacus.ai
Author: Abacus.AI
Author-email: dev@abacus.ai
License: MIT
Platform: UNKNOWN
Classifier: Development Status :: 5 - Production/Stable
Classifier: Intended Audience :: Developers
Classifier: Topic :: Utilities
Classifier: License :: OSI Approved :: MIT License
Classifier: Programming Language :: Python :: 3
Classifier: Programming Language :: Python :: 3.4
Classifier: Programming Language :: Python :: 3.5
Classifier: Programming Language :: Python :: 3.6
Classifier: Programming Language :: Python :: 3.7
